codemirror/__init__.py
codemirror/fields.py
codemirror/utils.py
codemirror/widgets.py
codemirror/addon/__init__.py
codemirror/addon/base.py
codemirror/addon/comment.py
codemirror/addon/edit.py
codemirror/addon/fold.py
codemirror/addon/hint.py
codemirror/addon/mode.py
mirror/__init__.py
mirror/admin.py
mirror/apps.py
mirror/forms.py
mirror/models.py
mirror/tests.py
mirror/urls.py
mirror/views.py
mirror/migrations/__init__.py
test_code/__init__.py
test_code/asgi.py
test_code/settings.py
test_code/urls.py
test_code/wsgi.py
django_codemirror_widget_2-0.0.2.dist-info/LICENSE.rst
django_codemirror_widget_2-0.0.2.dist-info/METADATA
django_codemirror_widget_2-0.0.2.dist-info/WHEEL
django_codemirror_widget_2-0.0.2.dist-info/top_level.txt
django_codemirror_widget_2-0.0.2.dist-info/zip-safe
django_codemirror_widget_2-0.0.2.dist-info/RECORD
