Metadata-Version: 2.1
Name: django-codemirror-widget-2
Version: 0.0.2
Summary: Django form widget library for using CodeMirror on textarea
Home-page: https://github.com/YutaUra/django-codemirror-widget
Author: Yuta Ura
Author-email: yuuta3594@outlook.jp
License: MIT
Keywords: django widget textarea codemirror
Platform: UNKNOWN
Classifier: Development Status :: 5 - Production/Stable
Classifier: Environment :: Web Environment
Classifier: Framework :: Django
Classifier: Intended Audience :: Developers
Classifier: License :: OSI Approved :: MIT License
Classifier: Programming Language :: Python
Classifier: Programming Language :: Python :: 3.8
Classifier: Topic :: Internet :: WWW/HTTP
Classifier: Topic :: Software Development :: Libraries
Classifier: Topic :: Software Development :: Libraries :: Application Frameworks
Classifier: Topic :: Software Development :: Libraries :: Python Modules
